cost_savings/cost_savings.py
cost_savings/manifest.toml
opsbox_cost_savings_assistant-0.1.2.dist-info/METADATA
opsbox_cost_savings_assistant-0.1.2.dist-info/WHEEL
opsbox_cost_savings_assistant-0.1.2.dist-info/entry_points.txt
opsbox_cost_savings_assistant-0.1.2.dist-info/top_level.txt
opsbox_cost_savings_assistant-0.1.2.dist-info/RECORD
