Metadata-Version: 2.1
Name: opsbox-cost-savings-assistant
Version: 0.1.2
Summary: Cost savings assistant for opsbox
Requires-Python: ==3.11.*
Requires-Dist: loguru>=0.7.3
Requires-Dist: pluggy>=1.5.0
